awslabs/__init__.py
awslabs/amazon_neptune_mcp_server/__init__.py
awslabs/amazon_neptune_mcp_server/exceptions.py
awslabs/amazon_neptune_mcp_server/models.py
awslabs/amazon_neptune_mcp_server/neptune.py
awslabs/amazon_neptune_mcp_server/server.py
awslabs/amazon_neptune_mcp_server/graph_store/__init__.py
awslabs/amazon_neptune_mcp_server/graph_store/analytics.py
awslabs/amazon_neptune_mcp_server/graph_store/base.py
awslabs/amazon_neptune_mcp_server/graph_store/database.py
awslabs_amazon_neptune_mcp_server-1.0.10.dist-info/METADATA
awslabs_amazon_neptune_mcp_server-1.0.10.dist-info/WHEEL
awslabs_amazon_neptune_mcp_server-1.0.10.dist-info/entry_points.txt
awslabs_amazon_neptune_mcp_server-1.0.10.dist-info/licenses/LICENSE
awslabs_amazon_neptune_mcp_server-1.0.10.dist-info/licenses/NOTICE
awslabs_amazon_neptune_mcp_server-1.0.10.dist-info/RECORD
